nonebot_plugin_repeater_count/__init__.py
nonebot_plugin_repeater_count/config.py
nonebot_plugin_repeater_count-0.1.1.dist-info/LICENSE
nonebot_plugin_repeater_count-0.1.1.dist-info/METADATA
nonebot_plugin_repeater_count-0.1.1.dist-info/WHEEL
nonebot_plugin_repeater_count-0.1.1.dist-info/RECORD
