Metadata-Version: 2.3
Name: nonebot-plugin-repeater-count
Version: 0.1.1
Summary: NoneBot 复读行为统计插件
License: MIT
Keywords: nonebot,repeater,statistics
Author: NIHTM 3605587449@qq.com
Requires-Python: >=3.8,<4.0
Classifier: License :: OSI Approved :: MIT License
Classifier: Programming Language :: Python :: 3
Classifier: Programming Language :: Python :: 3.8
Classifier: Programming Language :: Python :: 3.9
Classifier: Programming Language :: Python :: 3.10
Classifier: Programming Language :: Python :: 3.11
Classifier: Programming Language :: Python :: 3.12
Classifier: Programming Language :: Python :: 3.13
Requires-Dist: nonebot-adapter-onebot (>=2.2.0,<3.0.0)
Requires-Dist: nonebot2 (>=2.0.0,<3.0.0)
Project-URL: Homepage, https://github.com/name-is-hard-to-make/nonebot-plugin-repeater-count
